aiverify_digital_corruptions/__init__.py
aiverify_digital_corruptions/__main__.py
aiverify_digital_corruptions/algo.meta.json
aiverify_digital_corruptions/algo.py
aiverify_digital_corruptions/algo_init.py
aiverify_digital_corruptions/input.schema.json
aiverify_digital_corruptions/output.schema.json
aiverify_digital_corruptions/plugin_init.py
aiverify_digital_corruptions/utils/__init__.py
aiverify_digital_corruptions/utils/digital.py
aiverify_digital_corruptions-2.1.0.dist-info/METADATA
aiverify_digital_corruptions-2.1.0.dist-info/WHEEL
aiverify_digital_corruptions-2.1.0.dist-info/entry_points.txt
aiverify_digital_corruptions-2.1.0.dist-info/licenses/AUTHORS.rst
aiverify_digital_corruptions-2.1.0.dist-info/licenses/LICENSE
aiverify_digital_corruptions-2.1.0.dist-info/licenses/NOTICE.md
aiverify_digital_corruptions-2.1.0.dist-info/RECORD
